stock_quote/__init__.py
stock_quote-1.8.1.0.data/scripts/stock_quote
stock_quote-1.8.1.0.dist-info/METADATA
stock_quote-1.8.1.0.dist-info/WHEEL
stock_quote-1.8.1.0.dist-info/top_level.txt
stock_quote-1.8.1.0.dist-info/RECORD
