Metadata-Version: 2.1
Name: stock-quote
Version: 1.8.1.0
Summary: python script to get stock quotes and calculate gains and losses
Home-page: https://github.com/gps1539/stock_quote
Author: Graham Smith
Author-email: gps1539@gmail.com
License: GPL3
Download-URL: https://github.com/gps1539/stock_quote/archive/1.8.1.0.tar.gz
Keywords: testing,example
Platform: UNKNOWN
Requires-Python: >=3.5
Requires-Dist: numpy
Requires-Dist: colorama
Requires-Dist: influxdb
Requires-Dist: argparse
